paginate_json/__init__.py
paginate_json/cli.py
paginate_json-1.0.dist-info/LICENSE
paginate_json-1.0.dist-info/METADATA
paginate_json-1.0.dist-info/WHEEL
paginate_json-1.0.dist-info/entry_points.txt
paginate_json-1.0.dist-info/top_level.txt
paginate_json-1.0.dist-info/RECORD
