Metadata-Version: 2.1
Name: paginate-json
Version: 1.0
Summary: CLI tool for fetching paginated JSON from a URL
Home-page: https://github.com/simonw/paginate-json
Author: Simon Willison
License: Apache License, Version 2.0
Project-URL: Changelog, https://github.com/simonw/paginate-json/releases
Project-URL: Source code, https://github.com/simonw/paginate-json
Project-URL: Issues, https://github.com/simonw/paginate-json/issues
Project-URL: CI, https://github.com/simonw/paginate-json/actions
Classifier: Development Status :: 3 - Alpha
Classifier: Intended Audience :: Developers
Classifier: Intended Audience :: End Users/Desktop
Classifier: License :: OSI Approved :: Apache Software License
Classifier: Programming Language :: Python :: 3.6
Classifier: Programming Language :: Python :: 3.7
License-File: LICENSE
Requires-Dist: requests
Requires-Dist: click
Provides-Extra: pyjq
Requires-Dist: pyjq ; extra == 'pyjq'
Provides-Extra: test
Requires-Dist: pytest ; extra == 'test'
Requires-Dist: requests-mock ; extra == 'test'
Requires-Dist: cogapp ; extra == 'test'
